LICENSE-MIT
MANIFEST.in
README.rst
docopt_dispatch.py
setup.py
docopt_dispatch.egg-info/PKG-INFO
docopt_dispatch.egg-info/SOURCES.txt
docopt_dispatch.egg-info/dependency_links.txt
docopt_dispatch.egg-info/requires.txt
docopt_dispatch.egg-info/top_level.txt