Metadata-Version: 1.1
Name: docopt-dispatch
Version: 0.0.1
Summary: Dispatch from command-line arguments to functions
Home-page: https://github.com/halst/docopt-dispatch
Author: Vladimir Keleshev 
Author-email: vladimir@keleshev.com
License: MIT
Keywords: docopt dispatch function adapter kwargs
Platform: UNKNOWN
Classifier: Development Status :: 3 - Alpha
Classifier: Topic :: Utilities
Classifier: License :: OSI Approved :: MIT License
Classifier: Programming Language :: Python :: 2.5
Classifier: Programming Language :: Python :: 2.6
Classifier: Programming Language :: Python :: 2.7
Classifier: Programming Language :: Python :: 3.2
Classifier: Programming Language :: Python :: 3.3
